intentional_text_chat/__about__.py
intentional_text_chat/__init__.py
intentional_text_chat/bot_structure.py
intentional_text_chat-0.0.1rc1.dist-info/METADATA
intentional_text_chat-0.0.1rc1.dist-info/WHEEL
intentional_text_chat-0.0.1rc1.dist-info/licenses/LICENSE.txt
intentional_text_chat-0.0.1rc1.dist-info/RECORD
