Metadata-Version: 2.3
Name: intentional-text-chat
Version: 0.0.1rc1
Summary: Plugin that makes Intentional bots able to communicate through a turn-based text chat.
Project-URL: Documentation, https://github.com/intentional-ai/intentional#readme
Project-URL: Issues, https://github.com/intentional-ai/intentional/issues
Project-URL: Source, https://github.com/intentional-ai/intentional
Author-email: ZanSara <github@zansara.dev>
License: AGPL-3.0-or-later
Classifier: Development Status :: 4 - Beta
Classifier: Programming Language :: Python
Classifier: Programming Language :: Python :: 3.9
Classifier: Programming Language :: Python :: 3.10
Classifier: Programming Language :: Python :: 3.11
Classifier: Programming Language :: Python :: 3.12
Classifier: Programming Language :: Python :: Implementation :: CPython
Classifier: Programming Language :: Python :: Implementation :: PyPy
Requires-Python: >=3.9
Requires-Dist: intentional-core
Provides-Extra: dev
Requires-Dist: intentional[lint,test]; extra == 'dev'
Provides-Extra: lint
Requires-Dist: intentional[lint]; extra == 'lint'
Provides-Extra: test
Requires-Dist: intentional[test]; extra == 'test'
